.DS_Store
DeliberativePolling/__init__.py
test_package/__init__.py
DeliberativePolling-1.4.2.dist-info/METADATA
DeliberativePolling-1.4.2.dist-info/WHEEL
DeliberativePolling-1.4.2.dist-info/top_level.txt
DeliberativePolling-1.4.2.dist-info/RECORD
