Metadata-Version: 2.1
Name: DeliberativePolling
Version: 1.4.2
Summary: A package for analyzing survey data from Deliberative Polling experiments.
Home-page: https://github.com/WilloughbyWinograd/DeliberativePolling
Author: The Deliberative Democracy Lab at Stanford University
Author-email: deliberation@stanford.edu
License: MIT
Requires-Python: >=3.11
Requires-Dist: pandas
Requires-Dist: numpy
Requires-Dist: openpyxl
Requires-Dist: pyreadstat
Requires-Dist: statsmodels
Requires-Dist: scipy
Requires-Dist: docx
Requires-Dist: tqdm
Requires-Dist: python-docx
